py_filesearcher/__init__.py
py_filesearcher/indexer.py
py_filesearcher/readers/__init__.py
py_filesearcher/readers/archive.py
py_filesearcher/readers/base.py
py_filesearcher/readers/excel.py
py_filesearcher/readers/pdf.py
py_filesearcher/readers/text.py
py_filesearcher/readers/word.py
py_filesearcher-0.2.0.dist-info/METADATA
py_filesearcher-0.2.0.dist-info/WHEEL
py_filesearcher-0.2.0.dist-info/RECORD
